dbt_dbplyr/__init__.py
dbt_dbplyr/_compile.py
dbt_dbplyr/_dialects.py
dbt_dbplyr/_logging.py
dbt_dbplyr/_parse_dbt_project.py
dbt_dbplyr/_r_setup.py
dbt_dbplyr/_references.py
dbt_dbplyr/py.typed
dbt_dbplyr-0.1.0.dev0.dist-info/METADATA
dbt_dbplyr-0.1.0.dev0.dist-info/WHEEL
dbt_dbplyr-0.1.0.dev0.dist-info/entry_points.txt
dbt_dbplyr-0.1.0.dev0.dist-info/licenses/LICENSE
dbt_dbplyr-0.1.0.dev0.dist-info/RECORD
